lattica-1.0.19.dist-info/METADATA
lattica-1.0.19.dist-info/WHEEL
lattica/__init__.py
lattica/client.py
lattica/connection_handler.py
lattica_python_core/__init__.py
lattica_python_core/lattica_python_core.pyd
lattica-1.0.19.dist-info/RECORD
