Metadata-Version: 2.4
Name: lattica
Version: 1.0.19
Requires-Dist: asyncio ; python_full_version >= '3.8'
Requires-Dist: typing-extensions ; python_full_version < '3.8'
Requires-Dist: nest-asyncio ; python_full_version >= '3.8'
Requires-Dist: pytest>=7.0.0 ; extra == 'dev'
Requires-Dist: pytest-asyncio>=0.21.0 ; extra == 'dev'
Requires-Dist: pytest-cov>=4.0.0 ; extra == 'dev'
Requires-Dist: black>=23.0.0 ; extra == 'dev'
Requires-Dist: isort>=5.12.0 ; extra == 'dev'
Requires-Dist: flake8>=6.0.0 ; extra == 'dev'
Requires-Dist: mypy>=1.0.0 ; extra == 'dev'
Requires-Dist: psutil>=5.9.0 ; extra == 'dev'
Requires-Dist: pytest>=7.0.0 ; extra == 'test'
Requires-Dist: pytest-asyncio>=0.21.0 ; extra == 'test'
Requires-Dist: pytest-cov>=4.0.0 ; extra == 'test'
Requires-Dist: psutil>=5.9.0 ; extra == 'bench'
Requires-Dist: matplotlib>=3.7.0 ; extra == 'bench'
Requires-Dist: pandas>=2.0.0 ; extra == 'bench'
Provides-Extra: dev
Provides-Extra: test
Provides-Extra: bench
Summary: A unified Python SDK for P2P networking with integrated DHT and NAT capabilities
Keywords: p2p,networking,dht,nat,libp2p,distributed
License: MIT
Requires-Python: >=3.8
